pim/__init__.py
pim/cli.py
pim/util/pimfile_parser.py
pim_cli-0.2.1.dist-info/licenses/LICENSE
pim_cli-0.2.1.dist-info/METADATA
pim_cli-0.2.1.dist-info/WHEEL
pim_cli-0.2.1.dist-info/entry_points.txt
pim_cli-0.2.1.dist-info/top_level.txt
pim_cli-0.2.1.dist-info/RECORD
