Metadata-Version: 2.4
Name: pim-cli
Version: 0.2.1
Summary: A pip-inspired CLI tool for managing ML models via a Pimfile
Author-email: Maxim Mounier <maximmounier02@gmail.com>
License: MIT
Requires-Python: >=3.7
License-File: LICENSE
Requires-Dist: pyyaml
Dynamic: license-file
